optical_profilometry_feature_detection/__init__.py
optical_profilometry_feature_detection/batch_cracking.py
optical_profilometry_feature_detection/g_model_cracking.py
optical_profilometry_feature_detection/g_separate_lines.py
optical_profilometry_feature_detection/generate_plots.py
optical_profilometry_feature_detection-0.1.1.dist-info/METADATA
optical_profilometry_feature_detection-0.1.1.dist-info/WHEEL
optical_profilometry_feature_detection-0.1.1.dist-info/top_level.txt
optical_profilometry_feature_detection-0.1.1.dist-info/RECORD
