Metadata-Version: 2.1
Name: optical-profilometry-feature-detection
Version: 0.1.1
Summary: A suite of feature detection tools for optical profilometry data
Home-page: https://engineering.case.edu/centers/sdle/
Author: Kai Zheng, Priyan Rajamohan, Addison Klinke, Bereket Tadesse, Mirra Rasmussen, Mahamad Salah Mahmoud, Laura Bruckman
Author-email: zheng@case.edu, priyan@case.edu, agk38@case.edu, bereket.tadesse@case.edu, mirra.rasmussen@case.edu, mohamed.mahmoud2@case.edu, laura.bruckman@case.edu
License: BSD License (BSD-3)
Project-URL: Documentation, https://cwrusdle.bitbucket.io/sphinx/docs/build/html/index.html
Platform: UNKNOWN
Requires-Dist: numpy
Requires-Dist: scipy
Requires-Dist: statsmodels
Requires-Dist: pandas
